{"Neural Rendering": {"2303.09554": "|**2023-03-16**|**PartNeRF: Generating Part-Aware Editable 3D Shapes without 3D Supervision**|Konstantinos Tertikas et.al.|Leonidas Guibas|[2303.09554v1](http://arxiv.org/abs/2303.09554v1)|    |\n", "2303.09553": "|**2023-03-16**|**LERF: Language Embedded Radiance Fields**|Justin Kerr et.al.|Matthew Tancik|[2303.09553v1](http://arxiv.org/abs/2303.09553v1)|    |\n", "2303.09431": "|**2023-03-16**|**NeRFMeshing: Distilling Neural Radiance Fields into Geometrically-Accurate 3D Meshes**|Marie-Julie Rakotosaona et.al.|Federico Tombari|[2303.09431v1](http://arxiv.org/abs/2303.09431v1)|    |\n"}, "3D Reconstruction": {"2303.09554": "|**2023-03-16**|**PartNeRF: Generating Part-Aware Editable 3D Shapes without 3D Supervision**|Konstantinos Tertikas et.al.|Leonidas Guibas|[2303.09554v1](http://arxiv.org/abs/2303.09554v1)|    |\n", "2303.09553": "|**2023-03-16**|**LERF: Language Embedded Radiance Fields**|Justin Kerr et.al.|Matthew Tancik|[2303.09553v1](http://arxiv.org/abs/2303.09553v1)|    |\n", "2303.09551": "|**2023-03-16**|**SurroundOcc: Multi-Camera 3D Occupancy Prediction for Autonomous Driving**|Yi Wei et.al.|Jiwen Lu|[2303.09551v1](http://arxiv.org/abs/2303.09551v1)|**[code](https://github.com/weiyithu/surroundocc)**|\n", "2303.09544": "|**2023-03-16**|**Properties of 2D anyon gas**|Douglas Lundholm et.al.|Douglas Lundholm|[2303.09544v1](http://arxiv.org/abs/2303.09544v1)|    |\n", "2303.09541": "|**2023-03-16**|**Diffusion-HPC: Generating Synthetic Images with Realistic Humans**|Zhenzhen Weng et.al.|Serena Yeung|[2303.09541v1](http://arxiv.org/abs/2303.09541v1)|**[code](https://github.com/zzweng/diffusion_hpc)**|\n", "2303.09523": "|**2023-03-16**|**Fast 3D Volumetric Image Reconstruction from 2D MRI Slices by Parallel Processing**|Somoballi Ghoshal et.al.|Susmita Sur-Kolay|[2303.09523v1](http://arxiv.org/abs/2303.09523v1)|    |\n", "2303.09522": "|**2023-03-16**|**$P+$: Extended Textual Conditioning in Text-to-Image Generation**|Andrey Voynov et.al.|Kfir Aberman|[2303.09522v1](http://arxiv.org/abs/2303.09522v1)|    |\n", "2303.09495": "|**2023-03-16**|**Among Us: Adversarially Robust Collaborative Perception by Consensus**|Yiming Li et.al.|Chen Feng|[2303.09495v1](http://arxiv.org/abs/2303.09495v1)|**[code](https://github.com/coperception/robosac)**|\n", "2303.09486": "|**2023-03-16**|**Nontrivial absolutely continuous part of anomalous dissipation measures in time**|Carl Johan Peter Johansson et.al.|Massimo Sorella|[2303.09486v1](http://arxiv.org/abs/2303.09486v1)|    |\n", "2303.09431": "|**2023-03-16**|**NeRFMeshing: Distilling Neural Radiance Fields into Geometrically-Accurate 3D Meshes**|Marie-Julie Rakotosaona et.al.|Federico Tombari|[2303.09431v1](http://arxiv.org/abs/2303.09431v1)|    |\n", "2303.09410": "|**2023-03-16**|**Narrator: Towards Natural Control of Human-Scene Interaction Generation via Relationship Reasoning**|Haibiao Xuan et.al.|Kun Li|[2303.09410v1](http://arxiv.org/abs/2303.09410v1)|    |\n", "2303.09378": "|**2023-03-16**|**A phase-field model for non-small cell lung cancer under the effects of immunotherapy**|Andreas Wagner et.al.|Barbara Wohlmuth|[2303.09378v1](http://arxiv.org/abs/2303.09378v1)|    |\n"}, "Generative Models": {"2303.09556": "|**2023-03-16**|**Efficient Diffusion Training via Min-SNR Weighting Strategy**|Tiankai Hang et.al.|Baining Guo|[2303.09556v1](http://arxiv.org/abs/2303.09556v1)|    |\n", "2303.09555": "|**2023-03-16**|**SoftZoo: A Soft Robot Co-design Benchmark For Locomotion In Diverse Environments**|Tsun-Hsuan Wang et.al.|Chuang Gan|[2303.09555v1](http://arxiv.org/abs/2303.09555v1)|    |\n", "2303.09541": "|**2023-03-16**|**Diffusion-HPC: Generating Synthetic Images with Realistic Humans**|Zhenzhen Weng et.al.|Serena Yeung|[2303.09541v1](http://arxiv.org/abs/2303.09541v1)|**[code](https://github.com/zzweng/diffusion_hpc)**|\n", "2303.09522": "|**2023-03-16**|**$P+$: Extended Textual Conditioning in Text-to-Image Generation**|Andrey Voynov et.al.|Kfir Aberman|[2303.09522v1](http://arxiv.org/abs/2303.09522v1)|    |\n", "2303.09508": "|**2023-03-16**|**LDMVFI: Video Frame Interpolation with Latent Diffusion Models**|Duolikun Danier et.al.|David Bull|[2303.09508v1](http://arxiv.org/abs/2303.09508v1)|    |\n", "2303.09472": "|**2023-03-16**|**DiffIR: Efficient Diffusion Model for Image Restoration**|Bin Xia et.al.|Luc Van Gool|[2303.09472v1](http://arxiv.org/abs/2303.09472v1)|    |\n"}, "Scene Representation": {"2303.09554": "|**2023-03-16**|**PartNeRF: Generating Part-Aware Editable 3D Shapes without 3D Supervision**|Konstantinos Tertikas et.al.|Leonidas Guibas|[2303.09554v1](http://arxiv.org/abs/2303.09554v1)|    |\n", "2303.09431": "|**2023-03-16**|**NeRFMeshing: Distilling Neural Radiance Fields into Geometrically-Accurate 3D Meshes**|Marie-Julie Rakotosaona et.al.|Federico Tombari|[2303.09431v1](http://arxiv.org/abs/2303.09431v1)|    |\n", "2303.09152": "|**2023-03-16**|**Learning a Room with the Occ-SDF Hybrid: Signed Distance Function Mingled with Occupancy Aids Scene Representation**|Xiaoyang Lyu et.al.|Xiaojuan Qi|[2303.09152v1](http://arxiv.org/abs/2303.09152v1)|    |\n"}, "Geometry Processing": {"2303.09547": "|**2023-03-16**|**On Steiner Symmetrizations for First Exit Time Distributions**|Tim Rolling et.al.|Tim Rolling|[2303.09547v1](http://arxiv.org/abs/2303.09547v1)|    |\n", "2303.09537": "|**2023-03-16**|**Introduction to the Category of Derived Motivic Spectra**|Renaud Gauthier et.al.|Renaud Gauthier|[2303.09537v1](http://arxiv.org/abs/2303.09537v1)|    |\n", "2303.09536": "|**2023-03-16**|**Deep Metric Learning for Unsupervised Remote Sensing Change Detection**|Wele Gedara Chaminda Bandara et.al.|Vishal M. Patel|[2303.09536v1](http://arxiv.org/abs/2303.09536v1)|**[code](https://github.com/wgcban/metric-cd)**|\n"}}